setup.py
schmenkins/__init__.py
schmenkins/exceptions.py
schmenkins/state.py
schmenkins/utils.py
schmenkins.egg-info/PKG-INFO
schmenkins.egg-info/SOURCES.txt
schmenkins.egg-info/dependency_links.txt
schmenkins.egg-info/entry_points.txt
schmenkins.egg-info/pbr.json
schmenkins.egg-info/requires.txt
schmenkins.egg-info/top_level.txt
schmenkins/builders/__init__.py
schmenkins/builders/copyartifact.py
schmenkins/builders/shell.py
schmenkins/publishers/__init__.py
schmenkins/publishers/archive.py
schmenkins/publishers/trigger-parameterized-builds.py
schmenkins/scm/__init__.py
schmenkins/scm/git.py
schmenkins/tests/__init__.py
schmenkins/tests/test_main.py
schmenkins/tests/test_state.py
schmenkins/tests/test_utils.py
schmenkins/triggers/__init__.py
schmenkins/triggers/pollscm.py
schmenkins/triggers/timed.py