Metadata-Version: 1.0
Name: schmenkins
Version: 0.8
Summary: Jenkins Schmenkins
Home-page: http://schmenkins.net/
Author: Soren Hansen
Author-email: soren@linux2go.dk
License: UNKNOWN
Platform: UNKNOWN
